[
    {
        "is_tombstoned": false, 
        "kind": 1, 
        "program_year": 2017, 
        "task_instance_id": 5997880538038272, 
        "author": {
            "display_name": "Isaac Kamga", 
            "program_year": 2017, 
            "id": 5159751618920448
        }, 
        "text": "", 
        "created": "2017-12-17T15:02:39Z", 
        "task_definition_name": "Translate The Mifos Initiative Wikipedia Page Into Spanish (Espanol)", 
        "organization_id": 6239808655458304, 
        "author_is_student": false, 
        "new_task_instance_status": 7, 
        "author_id": 5159751618920448, 
        "id": 4533822286725120, 
        "old_task_instance_status": 4, 
        "attachments": []
    }, 
    {
        "is_tombstoned": false, 
        "kind": 1, 
        "program_year": 2017, 
        "task_instance_id": 5997880538038272, 
        "author": {
            "display_name": "Chirag Gupta", 
            "program_year": 2017, 
            "id": 6471766769664000
        }, 
        "text": "", 
        "created": "2017-12-17T13:11:08Z", 
        "task_definition_name": "Translate The Mifos Initiative Wikipedia Page Into Spanish (Espanol)", 
        "organization_id": 6239808655458304, 
        "author_is_student": true, 
        "new_task_instance_status": 4, 
        "author_id": 6471766769664000, 
        "id": 5082165056372736, 
        "old_task_instance_status": 5, 
        "attachments": []
    }, 
    {
        "is_tombstoned": false, 
        "kind": 1, 
        "program_year": 2017, 
        "task_instance_id": 5997880538038272, 
        "author": {
            "display_name": "Sanyam Goel", 
            "program_year": 2017, 
            "id": 4972460912934912
        }, 
        "text": "", 
        "created": "2017-12-17T12:23:11Z", 
        "task_definition_name": "Translate The Mifos Initiative Wikipedia Page Into Spanish (Espanol)", 
        "organization_id": 6239808655458304, 
        "author_is_student": false, 
        "new_task_instance_status": 5, 
        "author_id": 4972460912934912, 
        "id": 4893336550768640, 
        "old_task_instance_status": 4, 
        "attachments": []
    }, 
    {
        "is_tombstoned": false, 
        "kind": 2, 
        "program_year": 2017, 
        "task_instance_id": 5997880538038272, 
        "author": {
            "display_name": "Sanyam Goel", 
            "program_year": 2017, 
            "id": 4972460912934912
        }, 
        "text": "Hi Chirag!\nthe links in your documents seem to be broken.\nPlease correct them", 
        "created": "2017-12-17T12:23:05Z", 
        "task_definition_name": "Translate The Mifos Initiative Wikipedia Page Into Spanish (Espanol)", 
        "organization_id": 6239808655458304, 
        "author_is_student": false, 
        "new_task_instance_status": 4, 
        "author_id": 4972460912934912, 
        "id": 6645652874330112, 
        "old_task_instance_status": 4, 
        "attachments": []
    }, 
    {
        "is_tombstoned": false, 
        "kind": 2, 
        "program_year": 2017, 
        "task_instance_id": 5997880538038272, 
        "author": {
            "display_name": "Chirag Gupta", 
            "program_year": 2017, 
            "id": 6471766769664000
        }, 
        "text": "File: https://drive.google.com/open?id=1-LI69w6Ohu5CAyxZAwNUiYwTLjgSra4H", 
        "created": "2017-12-17T08:41:58Z", 
        "task_definition_name": "Translate The Mifos Initiative Wikipedia Page Into Spanish (Espanol)", 
        "organization_id": 6239808655458304, 
        "author_is_student": true, 
        "new_task_instance_status": 4, 
        "author_id": 6471766769664000, 
        "id": 5631280551034880, 
        "old_task_instance_status": 4, 
        "attachments": []
    }, 
    {
        "is_tombstoned": false, 
        "kind": 1, 
        "program_year": 2017, 
        "task_instance_id": 5997880538038272, 
        "author": {
            "display_name": "Chirag Gupta", 
            "program_year": 2017, 
            "id": 6471766769664000
        }, 
        "text": "", 
        "created": "2017-12-17T08:38:41Z", 
        "task_definition_name": "Translate The Mifos Initiative Wikipedia Page Into Spanish (Espanol)", 
        "organization_id": 6239808655458304, 
        "author_is_student": true, 
        "new_task_instance_status": 4, 
        "author_id": 6471766769664000, 
        "id": 4619803673231360, 
        "old_task_instance_status": 1, 
        "attachments": []
    }, 
    {
        "is_tombstoned": false, 
        "kind": 1, 
        "program_year": 2017, 
        "task_instance_id": 5997880538038272, 
        "author": {
            "display_name": "Chirag Gupta", 
            "program_year": 2017, 
            "id": 6471766769664000
        }, 
        "text": "", 
        "created": "2017-12-17T08:13:42Z", 
        "task_definition_name": "Translate The Mifos Initiative Wikipedia Page Into Spanish (Espanol)", 
        "organization_id": 6239808655458304, 
        "author_is_student": true, 
        "new_task_instance_status": 1, 
        "author_id": 6471766769664000, 
        "id": 5714866620858368, 
        "old_task_instance_status": 1, 
        "attachments": []
    }
]