[
    {
        "is_tombstoned": false, 
        "kind": 1, 
        "program_year": 2019, 
        "task_instance_id": 6268459348918272, 
        "author": {
            "display_name": "Mhk6", 
            "program_year": 2019, 
            "id": 5415227017920512
        }, 
        "text": "", 
        "created": "2019-12-29T04:18:55Z", 
        "task_definition_name": "Mifos Pay: Create A Round And Square Logo For MifosPay App", 
        "organization_id": 5721189306073088, 
        "author_is_student": true, 
        "new_task_instance_status": 2, 
        "author_id": 5415227017920512, 
        "id": 6040611300311040, 
        "old_task_instance_status": 5, 
        "attachments": []
    }, 
    {
        "is_tombstoned": false, 
        "kind": 1, 
        "program_year": 2019, 
        "task_instance_id": 6268459348918272, 
        "author": {
            "display_name": "Chirag Gupta", 
            "program_year": 2019, 
            "id": 5409251267182592
        }, 
        "text": "", 
        "created": "2019-12-28T16:50:50Z", 
        "task_definition_name": "Mifos Pay: Create A Round And Square Logo For MifosPay App", 
        "organization_id": 5721189306073088, 
        "author_is_student": false, 
        "new_task_instance_status": 5, 
        "author_id": 5409251267182592, 
        "id": 4936596801978368, 
        "old_task_instance_status": 4, 
        "attachments": []
    }, 
    {
        "is_tombstoned": false, 
        "kind": 2, 
        "program_year": 2019, 
        "task_instance_id": 6268459348918272, 
        "author": {
            "display_name": "Chirag Gupta", 
            "program_year": 2019, 
            "id": 5409251267182592
        }, 
        "text": "@Mhk6 I have not asked to copy it rather I need your original logos in those dimensions and shape. Take your time and do the task.", 
        "created": "2019-12-28T16:50:44Z", 
        "task_definition_name": "Mifos Pay: Create A Round And Square Logo For MifosPay App", 
        "organization_id": 5721189306073088, 
        "author_is_student": false, 
        "new_task_instance_status": 4, 
        "author_id": 5409251267182592, 
        "id": 6124417722089472, 
        "old_task_instance_status": 4, 
        "attachments": []
    }, 
    {
        "is_tombstoned": false, 
        "kind": 1, 
        "program_year": 2019, 
        "task_instance_id": 6268459348918272, 
        "author": {
            "display_name": "Mhk6", 
            "program_year": 2019, 
            "id": 5415227017920512
        }, 
        "text": "", 
        "created": "2019-12-28T11:53:56Z", 
        "task_definition_name": "Mifos Pay: Create A Round And Square Logo For MifosPay App", 
        "organization_id": 5721189306073088, 
        "author_is_student": true, 
        "new_task_instance_status": 4, 
        "author_id": 5415227017920512, 
        "id": 5349459391676416, 
        "old_task_instance_status": 5, 
        "attachments": []
    }, 
    {
        "is_tombstoned": false, 
        "kind": 2, 
        "program_year": 2019, 
        "task_instance_id": 6268459348918272, 
        "author": {
            "display_name": "Mhk6", 
            "program_year": 2019, 
            "id": 5415227017920512
        }, 
        "text": "", 
        "created": "2019-12-28T11:53:50Z", 
        "task_definition_name": "Mifos Pay: Create A Round And Square Logo For MifosPay App", 
        "organization_id": 5721189306073088, 
        "author_is_student": true, 
        "new_task_instance_status": 5, 
        "author_id": 5415227017920512, 
        "id": 4960902156124160, 
        "old_task_instance_status": 5, 
        "attachments": [
            {
                "file_type": "doc", 
                "url": "/serve/5269546089316352/", 
                "filename": "Designing_A_Logo-Mifos_Pay__3.jpg", 
                "id": 5269546089316352, 
                "file_size": 27513.0
            }, 
            {
                "file_type": "doc", 
                "url": "/serve/5823302866567168/", 
                "filename": "Designing_A_Logo-Mifos_Pay__4.png", 
                "id": 5823302866567168, 
                "file_size": 54983.0
            }
        ]
    }, 
    {
        "is_tombstoned": false, 
        "kind": 1, 
        "program_year": 2019, 
        "task_instance_id": 6268459348918272, 
        "author": {
            "display_name": "Chirag Gupta", 
            "program_year": 2019, 
            "id": 5409251267182592
        }, 
        "text": "", 
        "created": "2019-12-28T07:11:05Z", 
        "task_definition_name": "Mifos Pay: Create A Round And Square Logo For MifosPay App", 
        "organization_id": 5721189306073088, 
        "author_is_student": false, 
        "new_task_instance_status": 5, 
        "author_id": 5409251267182592, 
        "id": 6676385511243776, 
        "old_task_instance_status": 4, 
        "attachments": []
    }, 
    {
        "is_tombstoned": false, 
        "kind": 2, 
        "program_year": 2019, 
        "task_instance_id": 6268459348918272, 
        "author": {
            "display_name": "Chirag Gupta", 
            "program_year": 2019, 
            "id": 5409251267182592
        }, 
        "text": "@Mhk6 It is still not what we needed. Try to take a closer look at the example I have shared and try to fix it.", 
        "created": "2019-12-28T07:11:00Z", 
        "task_definition_name": "Mifos Pay: Create A Round And Square Logo For MifosPay App", 
        "organization_id": 5721189306073088, 
        "author_is_student": false, 
        "new_task_instance_status": 4, 
        "author_id": 5409251267182592, 
        "id": 5658373370937344, 
        "old_task_instance_status": 4, 
        "attachments": []
    }, 
    {
        "is_tombstoned": false, 
        "kind": 1, 
        "program_year": 2019, 
        "task_instance_id": 6268459348918272, 
        "author": {
            "display_name": "Mhk6", 
            "program_year": 2019, 
            "id": 5415227017920512
        }, 
        "text": "", 
        "created": "2019-12-27T00:30:28Z", 
        "task_definition_name": "Mifos Pay: Create A Round And Square Logo For MifosPay App", 
        "organization_id": 5721189306073088, 
        "author_is_student": true, 
        "new_task_instance_status": 4, 
        "author_id": 5415227017920512, 
        "id": 6325507352690688, 
        "old_task_instance_status": 5, 
        "attachments": []
    }, 
    {
        "is_tombstoned": false, 
        "kind": 2, 
        "program_year": 2019, 
        "task_instance_id": 6268459348918272, 
        "author": {
            "display_name": "Mhk6", 
            "program_year": 2019, 
            "id": 5415227017920512
        }, 
        "text": "", 
        "created": "2019-12-27T00:30:24Z", 
        "task_definition_name": "Mifos Pay: Create A Round And Square Logo For MifosPay App", 
        "organization_id": 5721189306073088, 
        "author_is_student": true, 
        "new_task_instance_status": 5, 
        "author_id": 5415227017920512, 
        "id": 5010636803670016, 
        "old_task_instance_status": 5, 
        "attachments": [
            {
                "file_type": "doc", 
                "url": "/serve/4524675816751104/", 
                "filename": "Designing_A_Logo-Mifos_Pay__2.jpg", 
                "id": 4524675816751104, 
                "file_size": 23306.0
            }, 
            {
                "file_type": "doc", 
                "url": "/serve/5089553673617408/", 
                "filename": "Designing_A_Logo-Mifos_Pay__3.png", 
                "id": 5089553673617408, 
                "file_size": 43522.0
            }
        ]
    }, 
    {
        "is_tombstoned": false, 
        "kind": 1, 
        "program_year": 2019, 
        "task_instance_id": 6268459348918272, 
        "author": {
            "display_name": "Chirag Gupta", 
            "program_year": 2019, 
            "id": 5409251267182592
        }, 
        "text": "", 
        "created": "2019-12-26T15:49:56Z", 
        "task_definition_name": "Mifos Pay: Create A Round And Square Logo For MifosPay App", 
        "organization_id": 5721189306073088, 
        "author_is_student": false, 
        "new_task_instance_status": 5, 
        "author_id": 5409251267182592, 
        "id": 5218325450194944, 
        "old_task_instance_status": 4, 
        "attachments": []
    }, 
    {
        "is_tombstoned": false, 
        "kind": 2, 
        "program_year": 2019, 
        "task_instance_id": 6268459348918272, 
        "author": {
            "display_name": "Chirag Gupta", 
            "program_year": 2019, 
            "id": 5409251267182592
        }, 
        "text": "It is not what we expected, maybe you are little confused.\n\nTry looking at this example - https://drive.google.com/drive/folders/1H19Lrxj6xxm3NDtgrzmdNpGgOLoDv5_B", 
        "created": "2019-12-26T15:49:52Z", 
        "task_definition_name": "Mifos Pay: Create A Round And Square Logo For MifosPay App", 
        "organization_id": 5721189306073088, 
        "author_is_student": false, 
        "new_task_instance_status": 4, 
        "author_id": 5409251267182592, 
        "id": 5259105493581824, 
        "old_task_instance_status": 4, 
        "attachments": []
    }, 
    {
        "is_tombstoned": false, 
        "kind": 1, 
        "program_year": 2019, 
        "task_instance_id": 6268459348918272, 
        "author": {
            "display_name": "Mhk6", 
            "program_year": 2019, 
            "id": 5415227017920512
        }, 
        "text": "", 
        "created": "2019-12-26T03:05:27Z", 
        "task_definition_name": "Mifos Pay: Create A Round And Square Logo For MifosPay App", 
        "organization_id": 5721189306073088, 
        "author_is_student": true, 
        "new_task_instance_status": 4, 
        "author_id": 5415227017920512, 
        "id": 6268363886559232, 
        "old_task_instance_status": 5, 
        "attachments": []
    }, 
    {
        "is_tombstoned": false, 
        "kind": 2, 
        "program_year": 2019, 
        "task_instance_id": 6268459348918272, 
        "author": {
            "display_name": "Mhk6", 
            "program_year": 2019, 
            "id": 5415227017920512
        }, 
        "text": "", 
        "created": "2019-12-26T00:59:06Z", 
        "task_definition_name": "Mifos Pay: Create A Round And Square Logo For MifosPay App", 
        "organization_id": 5721189306073088, 
        "author_is_student": true, 
        "new_task_instance_status": 5, 
        "author_id": 5415227017920512, 
        "id": 5856070380027904, 
        "old_task_instance_status": 5, 
        "attachments": [
            {
                "file_type": "doc", 
                "url": "/serve/4557026986819584/", 
                "filename": "Designing_A_Logo-Mifos_Pay__2.png", 
                "id": 4557026986819584, 
                "file_size": 66056.0
            }, 
            {
                "file_type": "doc", 
                "url": "/serve/4654203440463872/", 
                "filename": "Designing_A_Logo-Mifos_Pay__1.jpg", 
                "id": 4654203440463872, 
                "file_size": 29215.0
            }
        ]
    }, 
    {
        "is_tombstoned": false, 
        "kind": 1, 
        "program_year": 2019, 
        "task_instance_id": 6268459348918272, 
        "author": {
            "display_name": "Chirag Gupta", 
            "program_year": 2019, 
            "id": 5409251267182592
        }, 
        "text": "", 
        "created": "2019-12-25T16:53:32Z", 
        "task_definition_name": "Mifos Pay: Create A Round And Square Logo For MifosPay App", 
        "organization_id": 5721189306073088, 
        "author_is_student": false, 
        "new_task_instance_status": 5, 
        "author_id": 5409251267182592, 
        "id": 5201721844826112, 
        "old_task_instance_status": 4, 
        "attachments": []
    }, 
    {
        "is_tombstoned": false, 
        "kind": 2, 
        "program_year": 2019, 
        "task_instance_id": 6268459348918272, 
        "author": {
            "display_name": "Chirag Gupta", 
            "program_year": 2019, 
            "id": 5409251267182592
        }, 
        "text": "We are glad that you enjoyed doing this task.\n\nFeedback - Logo is fine but can you please give them in exact square and circle shape.", 
        "created": "2019-12-25T16:53:24Z", 
        "task_definition_name": "Mifos Pay: Create A Round And Square Logo For MifosPay App", 
        "organization_id": 5721189306073088, 
        "author_is_student": false, 
        "new_task_instance_status": 4, 
        "author_id": 5409251267182592, 
        "id": 5581004014616576, 
        "old_task_instance_status": 4, 
        "attachments": []
    }, 
    {
        "is_tombstoned": false, 
        "kind": 1, 
        "program_year": 2019, 
        "task_instance_id": 6268459348918272, 
        "author": {
            "display_name": "Mhk6", 
            "program_year": 2019, 
            "id": 5415227017920512
        }, 
        "text": "", 
        "created": "2019-12-24T12:48:35Z", 
        "task_definition_name": "Mifos Pay: Create A Round And Square Logo For MifosPay App", 
        "organization_id": 5721189306073088, 
        "author_is_student": true, 
        "new_task_instance_status": 4, 
        "author_id": 5415227017920512, 
        "id": 6175244163743744, 
        "old_task_instance_status": 1, 
        "attachments": []
    }, 
    {
        "is_tombstoned": false, 
        "kind": 2, 
        "program_year": 2019, 
        "task_instance_id": 6268459348918272, 
        "author": {
            "display_name": "Mhk6", 
            "program_year": 2019, 
            "id": 5415227017920512
        }, 
        "text": "This was a great experience; I've done other tasks but this is probably my favorite one.", 
        "created": "2019-12-24T12:47:16Z", 
        "task_definition_name": "Mifos Pay: Create A Round And Square Logo For MifosPay App", 
        "organization_id": 5721189306073088, 
        "author_is_student": true, 
        "new_task_instance_status": 1, 
        "author_id": 5415227017920512, 
        "id": 5578965264105472, 
        "old_task_instance_status": 1, 
        "attachments": [
            {
                "file_type": "doc", 
                "url": "/serve/5273765357813760/", 
                "filename": "Designing_A_Logo-Mifos_Pay_.png", 
                "id": 5273765357813760, 
                "file_size": 51838.0
            }, 
            {
                "file_type": "doc", 
                "url": "/serve/5716968334688256/", 
                "filename": "Designing_A_Logo-Mifos_Pay_.jpg", 
                "id": 5716968334688256, 
                "file_size": 26047.0
            }
        ]
    }, 
    {
        "is_tombstoned": true, 
        "kind": 2, 
        "program_year": 2019, 
        "task_instance_id": 6268459348918272, 
        "author": {
            "display_name": "Mhk6", 
            "program_year": 2019, 
            "id": 5415227017920512
        }, 
        "text": "", 
        "created": "2019-12-24T12:46:23Z", 
        "task_definition_name": "Mifos Pay: Create A Round And Square Logo For MifosPay App", 
        "organization_id": 5721189306073088, 
        "author_is_student": true, 
        "new_task_instance_status": 1, 
        "author_id": 5415227017920512, 
        "id": 5513084492316672, 
        "old_task_instance_status": 1, 
        "attachments": []
    }, 
    {
        "is_tombstoned": false, 
        "kind": 1, 
        "program_year": 2019, 
        "task_instance_id": 6268459348918272, 
        "author": {
            "display_name": "Mhk6", 
            "program_year": 2019, 
            "id": 5415227017920512
        }, 
        "text": "", 
        "created": "2019-12-24T12:15:32Z", 
        "task_definition_name": "Mifos Pay: Create A Round And Square Logo For MifosPay App", 
        "organization_id": 5721189306073088, 
        "author_is_student": true, 
        "new_task_instance_status": 1, 
        "author_id": 5415227017920512, 
        "id": 6061685429764096, 
        "old_task_instance_status": 1, 
        "attachments": []
    }
]