[
    {
        "is_tombstoned": false, 
        "kind": 1, 
        "program_year": 2017, 
        "task_instance_id": 5102748200599552, 
        "author": {
            "display_name": "Sarvesh", 
            "program_year": 2017, 
            "id": 6674862124826624
        }, 
        "text": "", 
        "created": "2018-01-04T16:01:06Z", 
        "task_definition_name": "Join the Mifos Community and Introduce Yourself!", 
        "organization_id": 6239808655458304, 
        "author_is_student": true, 
        "new_task_instance_status": 2, 
        "author_id": 6674862124826624, 
        "id": 5701658640121856, 
        "old_task_instance_status": 1, 
        "attachments": []
    }, 
    {
        "is_tombstoned": false, 
        "kind": 1, 
        "program_year": 2017, 
        "task_instance_id": 5102748200599552, 
        "author": {
            "display_name": "Sarvesh", 
            "program_year": 2017, 
            "id": 6674862124826624
        }, 
        "text": "", 
        "created": "2018-01-04T15:56:14Z", 
        "task_definition_name": "Join the Mifos Community and Introduce Yourself!", 
        "organization_id": 6239808655458304, 
        "author_is_student": true, 
        "new_task_instance_status": 1, 
        "author_id": 6674862124826624, 
        "id": 5431533852688384, 
        "old_task_instance_status": 1, 
        "attachments": []
    }
]