[
    {
        "is_tombstoned": false, 
        "kind": 1, 
        "program_year": 2017, 
        "task_instance_id": 5707683137060864, 
        "author": {
            "display_name": "Edward Cable", 
            "program_year": 2017, 
            "id": 5740383550046208
        }, 
        "text": "", 
        "created": "2018-01-02T23:06:05Z", 
        "task_definition_name": "Write a Research Brief on PSD2 Payment Services Directive", 
        "organization_id": 6239808655458304, 
        "author_is_student": false, 
        "new_task_instance_status": 7, 
        "author_id": 5740383550046208, 
        "id": 5114394541293568, 
        "old_task_instance_status": 4, 
        "attachments": []
    }, 
    {
        "is_tombstoned": false, 
        "kind": 2, 
        "program_year": 2017, 
        "task_instance_id": 5707683137060864, 
        "author": {
            "display_name": "Edward Cable", 
            "program_year": 2017, 
            "id": 5740383550046208
        }, 
        "text": "Nice work.", 
        "created": "2018-01-02T23:05:59Z", 
        "task_definition_name": "Write a Research Brief on PSD2 Payment Services Directive", 
        "organization_id": 6239808655458304, 
        "author_is_student": false, 
        "new_task_instance_status": 4, 
        "author_id": 5740383550046208, 
        "id": 5860790668099584, 
        "old_task_instance_status": 4, 
        "attachments": []
    }, 
    {
        "is_tombstoned": false, 
        "kind": 1, 
        "program_year": 2017, 
        "task_instance_id": 5707683137060864, 
        "author": {
            "display_name": "janicek", 
            "program_year": 2017, 
            "id": 5742982516965376
        }, 
        "text": "", 
        "created": "2018-01-02T22:50:23Z", 
        "task_definition_name": "Write a Research Brief on PSD2 Payment Services Directive", 
        "organization_id": 6239808655458304, 
        "author_is_student": true, 
        "new_task_instance_status": 4, 
        "author_id": 5742982516965376, 
        "id": 4712463113125888, 
        "old_task_instance_status": 1, 
        "attachments": []
    }, 
    {
        "is_tombstoned": false, 
        "kind": 2, 
        "program_year": 2017, 
        "task_instance_id": 5707683137060864, 
        "author": {
            "display_name": "janicek", 
            "program_year": 2017, 
            "id": 5742982516965376
        }, 
        "text": "Hello,\nI have submitted the research brief to the folder. A direct link:\nhttps://docs.google.com/document/d/1lZtqtcgKeVLCGohigoVc_S1iKExBZWFKtnic3SQnDJk/edit?usp=sharing\n\nThank you!\nJanice K.", 
        "created": "2018-01-02T22:50:19Z", 
        "task_definition_name": "Write a Research Brief on PSD2 Payment Services Directive", 
        "organization_id": 6239808655458304, 
        "author_is_student": true, 
        "new_task_instance_status": 1, 
        "author_id": 5742982516965376, 
        "id": 5884213540683776, 
        "old_task_instance_status": 1, 
        "attachments": []
    }, 
    {
        "is_tombstoned": false, 
        "kind": 1, 
        "program_year": 2017, 
        "task_instance_id": 5707683137060864, 
        "author": {
            "display_name": "janicek", 
            "program_year": 2017, 
            "id": 5742982516965376
        }, 
        "text": "", 
        "created": "2018-01-02T12:13:57Z", 
        "task_definition_name": "Write a Research Brief on PSD2 Payment Services Directive", 
        "organization_id": 6239808655458304, 
        "author_is_student": true, 
        "new_task_instance_status": 1, 
        "author_id": 5742982516965376, 
        "id": 5572424080818176, 
        "old_task_instance_status": 1, 
        "attachments": []
    }
]