[
    {
        "is_tombstoned": false, 
        "kind": 1, 
        "program_year": 2017, 
        "task_instance_id": 5963863264591872, 
        "author": null, 
        "text": "", 
        "created": "2017-12-06T23:44:47Z", 
        "task_definition_name": "Correct Spelling And Capitalization Of Role Name ( Correct Spelling )", 
        "organization_id": 6239808655458304, 
        "author_is_student": false, 
        "new_task_instance_status": 6, 
        "author_id": null, 
        "id": 5958503774552064, 
        "old_task_instance_status": 1, 
        "attachments": []
    }, 
    {
        "is_tombstoned": false, 
        "kind": 1, 
        "program_year": 2017, 
        "task_instance_id": 5963863264591872, 
        "author": {
            "display_name": "Tomi Adetunji", 
            "program_year": 2017, 
            "id": 6278858313564160
        }, 
        "text": "", 
        "created": "2017-12-03T23:44:25Z", 
        "task_definition_name": "Correct Spelling And Capitalization Of Role Name ( Correct Spelling )", 
        "organization_id": 6239808655458304, 
        "author_is_student": true, 
        "new_task_instance_status": 1, 
        "author_id": 6278858313564160, 
        "id": 6597615753887744, 
        "old_task_instance_status": 1, 
        "attachments": []
    }
]