[
    {
        "is_tombstoned": false, 
        "kind": 1, 
        "program_year": 2018, 
        "task_instance_id": 4644215670702080, 
        "author": {
            "display_name": "abhaychawla", 
            "program_year": 2018, 
            "id": 4574209805123584
        }, 
        "text": "", 
        "created": "2018-12-08T16:06:34Z", 
        "task_definition_name": "Mifos - Create A Hooks Component And Design Its User Interface In Mifos X Web App", 
        "organization_id": 4752143387983872, 
        "author_is_student": false, 
        "new_task_instance_status": 7, 
        "author_id": 4574209805123584, 
        "id": 5434128104161280, 
        "old_task_instance_status": 4, 
        "attachments": []
    }, 
    {
        "is_tombstoned": false, 
        "kind": 2, 
        "program_year": 2018, 
        "task_instance_id": 4644215670702080, 
        "author": {
            "display_name": "abhaychawla", 
            "program_year": 2018, 
            "id": 4574209805123584
        }, 
        "text": "Nice work! :)", 
        "created": "2018-12-08T16:06:29Z", 
        "task_definition_name": "Mifos - Create A Hooks Component And Design Its User Interface In Mifos X Web App", 
        "organization_id": 4752143387983872, 
        "author_is_student": false, 
        "new_task_instance_status": 4, 
        "author_id": 4574209805123584, 
        "id": 5387982405107712, 
        "old_task_instance_status": 4, 
        "attachments": []
    }, 
    {
        "is_tombstoned": false, 
        "kind": 2, 
        "program_year": 2018, 
        "task_instance_id": 4644215670702080, 
        "author": {
            "display_name": "abhaychawla", 
            "program_year": 2018, 
            "id": 4574209805123584
        }, 
        "text": "Documentation refers to comments within the web app for the functions/components you have implemented only.", 
        "created": "2018-12-08T16:05:50Z", 
        "task_definition_name": "Mifos - Create A Hooks Component And Design Its User Interface In Mifos X Web App", 
        "organization_id": 4752143387983872, 
        "author_is_student": false, 
        "new_task_instance_status": 4, 
        "author_id": 4574209805123584, 
        "id": 6592710531088384, 
        "old_task_instance_status": 4, 
        "attachments": []
    }, 
    {
        "is_tombstoned": false, 
        "kind": 2, 
        "program_year": 2018, 
        "task_instance_id": 4644215670702080, 
        "author": {
            "display_name": "jz53", 
            "program_year": 2018, 
            "id": 4890377967370240
        }, 
        "text": "Actually, seeing that the components are not completely done (still don't have create/view/edit), I guess documentation would be a bit harder (I tried to start some). I guess I will work on some more tasks then.", 
        "created": "2018-12-08T14:20:56Z", 
        "task_definition_name": "Mifos - Create A Hooks Component And Design Its User Interface In Mifos X Web App", 
        "organization_id": 4752143387983872, 
        "author_is_student": true, 
        "new_task_instance_status": 4, 
        "author_id": 4890377967370240, 
        "id": 5485319718699008, 
        "old_task_instance_status": 4, 
        "attachments": []
    }, 
    {
        "is_tombstoned": false, 
        "kind": 2, 
        "program_year": 2018, 
        "task_instance_id": 4644215670702080, 
        "author": {
            "display_name": "jz53", 
            "program_year": 2018, 
            "id": 4890377967370240
        }, 
        "text": "I would also like to go back and do the documentation for the screens that I have completed. Is there an example documentation that I can go off of in order to make them for my tasks?\n\nIt would be nice if I could get this task submitted though, I have worked a bit ahead on my free time to complete another component (at my own risk).", 
        "created": "2018-12-08T13:57:35Z", 
        "task_definition_name": "Mifos - Create A Hooks Component And Design Its User Interface In Mifos X Web App", 
        "organization_id": 4752143387983872, 
        "author_is_student": true, 
        "new_task_instance_status": 4, 
        "author_id": 4890377967370240, 
        "id": 5442176201785344, 
        "old_task_instance_status": 4, 
        "attachments": []
    }, 
    {
        "is_tombstoned": false, 
        "kind": 2, 
        "program_year": 2018, 
        "task_instance_id": 4644215670702080, 
        "author": {
            "display_name": "jz53", 
            "program_year": 2018, 
            "id": 4890377967370240
        }, 
        "text": "Added your suggestion, updated with gif/screenshot. :)", 
        "created": "2018-12-08T13:03:28Z", 
        "task_definition_name": "Mifos - Create A Hooks Component And Design Its User Interface In Mifos X Web App", 
        "organization_id": 4752143387983872, 
        "author_is_student": true, 
        "new_task_instance_status": 4, 
        "author_id": 4890377967370240, 
        "id": 6168216096210944, 
        "old_task_instance_status": 4, 
        "attachments": []
    }, 
    {
        "is_tombstoned": false, 
        "kind": 1, 
        "program_year": 2018, 
        "task_instance_id": 4644215670702080, 
        "author": {
            "display_name": "jz53", 
            "program_year": 2018, 
            "id": 4890377967370240
        }, 
        "text": "", 
        "created": "2018-12-08T12:56:28Z", 
        "task_definition_name": "Mifos - Create A Hooks Component And Design Its User Interface In Mifos X Web App", 
        "organization_id": 4752143387983872, 
        "author_is_student": true, 
        "new_task_instance_status": 4, 
        "author_id": 4890377967370240, 
        "id": 5658074309197824, 
        "old_task_instance_status": 1, 
        "attachments": []
    }, 
    {
        "is_tombstoned": false, 
        "kind": 2, 
        "program_year": 2018, 
        "task_instance_id": 4644215670702080, 
        "author": {
            "display_name": "jz53", 
            "program_year": 2018, 
            "id": 4890377967370240
        }, 
        "text": "https://github.com/openMF/web-app/pull/339", 
        "created": "2018-12-08T04:16:32Z", 
        "task_definition_name": "Mifos - Create A Hooks Component And Design Its User Interface In Mifos X Web App", 
        "organization_id": 4752143387983872, 
        "author_is_student": true, 
        "new_task_instance_status": 1, 
        "author_id": 4890377967370240, 
        "id": 6404636329115648, 
        "old_task_instance_status": 1, 
        "attachments": []
    }, 
    {
        "is_tombstoned": false, 
        "kind": 1, 
        "program_year": 2018, 
        "task_instance_id": 4644215670702080, 
        "author": {
            "display_name": "jz53", 
            "program_year": 2018, 
            "id": 4890377967370240
        }, 
        "text": "", 
        "created": "2018-12-07T19:25:11Z", 
        "task_definition_name": "Mifos - Create A Hooks Component And Design Its User Interface In Mifos X Web App", 
        "organization_id": 4752143387983872, 
        "author_is_student": true, 
        "new_task_instance_status": 1, 
        "author_id": 4890377967370240, 
        "id": 4746061626212352, 
        "old_task_instance_status": 1, 
        "attachments": []
    }
]