{
    "student_display_name": "Leon", 
    "status": "ABANDONED", 
    "program_year": 2019, 
    "task_definition_id": 6382743907205120, 
    "tags": [
        " social media", 
        " marketing", 
        " mifos", 
        "outreach", 
        " design"
    ], 
    "student_id": 5469072829972480, 
    "is_beginner": "False", 
    "time_to_complete_in_days": "3", 
    "modified": "2019-12-05 09:46:42", 
    "max_instances": "10", 
    "id": 5398776026497024, 
    "organization_name": "The Mifos Initiative", 
    "completion_date": null, 
    "deadline": "2019-12-08 09:45:43", 
    "submitted_date": null, 
    "organization_id": 5721189306073088, 
    "mentors": [
        "jddeep003@gmail.com", 
        "edcable@mifos.org", 
        "luphieanza@gmail.com", 
        "guptachirag2002@gmail.com"
    ], 
    "task_definition_name": "Create a Holiday Greeting Card/Banner for Mifos Initiative", 
    "categories": [
        "2", 
        "5"
    ], 
    "description": "This task involves designing a greeting card and/or banner for Mifos, wishing happy holidays (holidays in general, Christmas, Kwanza, Diwali, Hanukkah, etc)\n\nMake it look good, something you'd be proud to show to family and friends. We'd love to be able to use this in our email banners that we send out this year and on social media so please include multiple sizes of your design. The ideal size for banners is 600 to 700 pixels wide and 100-200 pixels high. For instagram, dimensions should be 1080x1080. For facebook, 1200x630.\n\nSubmit your artwork in both .jpg and .png format and please include the native file (.ai, .psd, or .eps) file format. \n\nMifos logos can be found at https://drive.google.com/open?id=0ByeK44WJrHIvYnk1M0ZFemJSNkE \n\nAlso, append your name to the submitted file here, https://drive.google.com/open?id=1DOWBCUw54XP1g7p03FjD_33hVtPb_ABn, so that we know who did the work."
}