[
    {
        "is_tombstoned": false, 
        "kind": 1, 
        "program_year": 2017, 
        "task_instance_id": 6012343823630336, 
        "author": {
            "display_name": "Edward Cable", 
            "program_year": 2017, 
            "id": 5740383550046208
        }, 
        "text": "", 
        "created": "2018-01-03T14:41:47Z", 
        "task_definition_name": "Write a Research Brief on PSD2 Payment Services Directive", 
        "organization_id": 6239808655458304, 
        "author_is_student": false, 
        "new_task_instance_status": 7, 
        "author_id": 5740383550046208, 
        "id": 5569694360666112, 
        "old_task_instance_status": 4, 
        "attachments": []
    }, 
    {
        "is_tombstoned": false, 
        "kind": 1, 
        "program_year": 2017, 
        "task_instance_id": 6012343823630336, 
        "author": {
            "display_name": "luphieanza", 
            "program_year": 2017, 
            "id": 5733321055141888
        }, 
        "text": "", 
        "created": "2018-01-03T11:33:55Z", 
        "task_definition_name": "Write a Research Brief on PSD2 Payment Services Directive", 
        "organization_id": 6239808655458304, 
        "author_is_student": true, 
        "new_task_instance_status": 4, 
        "author_id": 5733321055141888, 
        "id": 4811090191974400, 
        "old_task_instance_status": 1, 
        "attachments": []
    }, 
    {
        "is_tombstoned": false, 
        "kind": 2, 
        "program_year": 2017, 
        "task_instance_id": 6012343823630336, 
        "author": {
            "display_name": "luphieanza", 
            "program_year": 2017, 
            "id": 5733321055141888
        }, 
        "text": "Hello Mr.Edcable, here my work at https://goo.gl/cFo7Bt, thanks", 
        "created": "2018-01-03T11:33:33Z", 
        "task_definition_name": "Write a Research Brief on PSD2 Payment Services Directive", 
        "organization_id": 6239808655458304, 
        "author_is_student": true, 
        "new_task_instance_status": 1, 
        "author_id": 5733321055141888, 
        "id": 6311825048076288, 
        "old_task_instance_status": 1, 
        "attachments": []
    }, 
    {
        "is_tombstoned": false, 
        "kind": 1, 
        "program_year": 2017, 
        "task_instance_id": 6012343823630336, 
        "author": {
            "display_name": "luphieanza", 
            "program_year": 2017, 
            "id": 5733321055141888
        }, 
        "text": "", 
        "created": "2018-01-03T11:32:08Z", 
        "task_definition_name": "Write a Research Brief on PSD2 Payment Services Directive", 
        "organization_id": 6239808655458304, 
        "author_is_student": true, 
        "new_task_instance_status": 1, 
        "author_id": 5733321055141888, 
        "id": 4906551410163712, 
        "old_task_instance_status": 1, 
        "attachments": []
    }
]