[
    {
        "is_tombstoned": false, 
        "kind": 1, 
        "program_year": 2019, 
        "task_instance_id": 5891771339374592, 
        "author": {
            "display_name": "jddeep", 
            "program_year": 2019, 
            "id": 5515255220797440
        }, 
        "text": "", 
        "created": "2020-01-13T16:16:10Z", 
        "task_definition_name": "Write a Fintech Research Brief on Digital Financial Services in Malawi", 
        "organization_id": 5721189306073088, 
        "author_is_student": false, 
        "new_task_instance_status": 7, 
        "author_id": 5515255220797440, 
        "id": 6300571846311936, 
        "old_task_instance_status": 4, 
        "attachments": []
    }, 
    {
        "is_tombstoned": false, 
        "kind": 2, 
        "program_year": 2019, 
        "task_instance_id": 5891771339374592, 
        "author": {
            "display_name": "jddeep", 
            "program_year": 2019, 
            "id": 5515255220797440
        }, 
        "text": "LGTM :)", 
        "created": "2020-01-13T16:16:02Z", 
        "task_definition_name": "Write a Fintech Research Brief on Digital Financial Services in Malawi", 
        "organization_id": 5721189306073088, 
        "author_is_student": false, 
        "new_task_instance_status": 4, 
        "author_id": 5515255220797440, 
        "id": 6592965368086528, 
        "old_task_instance_status": 4, 
        "attachments": []
    }, 
    {
        "is_tombstoned": false, 
        "kind": 1, 
        "program_year": 2019, 
        "task_instance_id": 5891771339374592, 
        "author": {
            "display_name": "PiyushSharma99", 
            "program_year": 2019, 
            "id": 6483083604262912
        }, 
        "text": "", 
        "created": "2020-01-13T16:14:13Z", 
        "task_definition_name": "Write a Fintech Research Brief on Digital Financial Services in Malawi", 
        "organization_id": 5721189306073088, 
        "author_is_student": true, 
        "new_task_instance_status": 4, 
        "author_id": 6483083604262912, 
        "id": 6675756030099456, 
        "old_task_instance_status": 1, 
        "attachments": []
    }, 
    {
        "is_tombstoned": false, 
        "kind": 2, 
        "program_year": 2019, 
        "task_instance_id": 5891771339374592, 
        "author": {
            "display_name": "PiyushSharma99", 
            "program_year": 2019, 
            "id": 6483083604262912
        }, 
        "text": "Here is my submission to the task - https://docs.google.com/document/d/1jI6OCbKrC4_1PcGx08VuGa7TmDFvo4SxTlTZZPMfSms/edit?usp=sharing\nThanks!", 
        "created": "2020-01-13T16:14:09Z", 
        "task_definition_name": "Write a Fintech Research Brief on Digital Financial Services in Malawi", 
        "organization_id": 5721189306073088, 
        "author_is_student": true, 
        "new_task_instance_status": 1, 
        "author_id": 6483083604262912, 
        "id": 5369619431292928, 
        "old_task_instance_status": 1, 
        "attachments": []
    }, 
    {
        "is_tombstoned": false, 
        "kind": 1, 
        "program_year": 2019, 
        "task_instance_id": 5891771339374592, 
        "author": {
            "display_name": "PiyushSharma99", 
            "program_year": 2019, 
            "id": 6483083604262912
        }, 
        "text": "", 
        "created": "2020-01-13T15:42:54Z", 
        "task_definition_name": "Write a Fintech Research Brief on Digital Financial Services in Malawi", 
        "organization_id": 5721189306073088, 
        "author_is_student": true, 
        "new_task_instance_status": 1, 
        "author_id": 6483083604262912, 
        "id": 5626493036658688, 
        "old_task_instance_status": 1, 
        "attachments": []
    }
]