[
    {
        "is_tombstoned": false, 
        "kind": 1, 
        "program_year": 2018, 
        "task_instance_id": 5056383587188736, 
        "author": {
            "display_name": "Ankit Raj Ojha", 
            "program_year": 2018, 
            "id": 5746296582307840
        }, 
        "text": "", 
        "created": "2018-11-06T19:23:28Z", 
        "task_definition_name": "Mifos - Bug Fix: On employee creation, \"joined on\" field has no sign of showing it mandatory", 
        "organization_id": 4752143387983872, 
        "author_is_student": false, 
        "new_task_instance_status": 7, 
        "author_id": 5746296582307840, 
        "id": 5160118736912384, 
        "old_task_instance_status": 4, 
        "attachments": []
    }, 
    {
        "is_tombstoned": false, 
        "kind": 2, 
        "program_year": 2018, 
        "task_instance_id": 5056383587188736, 
        "author": {
            "display_name": "Malaal Dehlvi", 
            "program_year": 2018, 
            "id": 5288972474384384
        }, 
        "text": "I have updated the PR. Please review. :)", 
        "created": "2018-11-06T19:02:12Z", 
        "task_definition_name": "Mifos - Bug Fix: On employee creation, \"joined on\" field has no sign of showing it mandatory", 
        "organization_id": 4752143387983872, 
        "author_is_student": true, 
        "new_task_instance_status": 4, 
        "author_id": 5288972474384384, 
        "id": 6709632274792448, 
        "old_task_instance_status": 4, 
        "attachments": []
    }, 
    {
        "is_tombstoned": false, 
        "kind": 1, 
        "program_year": 2018, 
        "task_instance_id": 5056383587188736, 
        "author": {
            "display_name": "Malaal Dehlvi", 
            "program_year": 2018, 
            "id": 5288972474384384
        }, 
        "text": "", 
        "created": "2018-11-06T19:01:57Z", 
        "task_definition_name": "Mifos - Bug Fix: On employee creation, \"joined on\" field has no sign of showing it mandatory", 
        "organization_id": 4752143387983872, 
        "author_is_student": true, 
        "new_task_instance_status": 4, 
        "author_id": 5288972474384384, 
        "id": 6510036273594368, 
        "old_task_instance_status": 5, 
        "attachments": []
    }, 
    {
        "is_tombstoned": false, 
        "kind": 2, 
        "program_year": 2018, 
        "task_instance_id": 5056383587188736, 
        "author": {
            "display_name": "Malaal Dehlvi", 
            "program_year": 2018, 
            "id": 5288972474384384
        }, 
        "text": "I commented on the PR. Please reply. :)", 
        "created": "2018-11-06T01:41:37Z", 
        "task_definition_name": "Mifos - Bug Fix: On employee creation, \"joined on\" field has no sign of showing it mandatory", 
        "organization_id": 4752143387983872, 
        "author_is_student": true, 
        "new_task_instance_status": 5, 
        "author_id": 5288972474384384, 
        "id": 6456769296465920, 
        "old_task_instance_status": 5, 
        "attachments": []
    }, 
    {
        "is_tombstoned": false, 
        "kind": 2, 
        "program_year": 2018, 
        "task_instance_id": 5056383587188736, 
        "author": {
            "display_name": "Gopala", 
            "program_year": 2018, 
            "id": 6351985419747328
        }, 
        "text": "Hi Mallal, Please take a look at the comments on the PR, feel free to ask if you have any questions ;)", 
        "created": "2018-11-05T08:17:53Z", 
        "task_definition_name": "Mifos - Bug Fix: On employee creation, \"joined on\" field has no sign of showing it mandatory", 
        "organization_id": 4752143387983872, 
        "author_is_student": false, 
        "new_task_instance_status": 5, 
        "author_id": 6351985419747328, 
        "id": 5320226649407488, 
        "old_task_instance_status": 5, 
        "attachments": []
    }, 
    {
        "is_tombstoned": false, 
        "kind": 1, 
        "program_year": 2018, 
        "task_instance_id": 5056383587188736, 
        "author": {
            "display_name": "Gopala", 
            "program_year": 2018, 
            "id": 6351985419747328
        }, 
        "text": "", 
        "created": "2018-11-05T08:17:31Z", 
        "task_definition_name": "Mifos - Bug Fix: On employee creation, \"joined on\" field has no sign of showing it mandatory", 
        "organization_id": 4752143387983872, 
        "author_is_student": false, 
        "new_task_instance_status": 5, 
        "author_id": 6351985419747328, 
        "id": 5735383825383424, 
        "old_task_instance_status": 4, 
        "attachments": []
    }, 
    {
        "is_tombstoned": false, 
        "kind": 1, 
        "program_year": 2018, 
        "task_instance_id": 5056383587188736, 
        "author": {
            "display_name": "Malaal Dehlvi", 
            "program_year": 2018, 
            "id": 5288972474384384
        }, 
        "text": "", 
        "created": "2018-11-04T17:00:25Z", 
        "task_definition_name": "Mifos - Bug Fix: On employee creation, \"joined on\" field has no sign of showing it mandatory", 
        "organization_id": 4752143387983872, 
        "author_is_student": true, 
        "new_task_instance_status": 4, 
        "author_id": 5288972474384384, 
        "id": 6704014189133824, 
        "old_task_instance_status": 1, 
        "attachments": []
    }, 
    {
        "is_tombstoned": false, 
        "kind": 2, 
        "program_year": 2018, 
        "task_instance_id": 5056383587188736, 
        "author": {
            "display_name": "Malaal Dehlvi", 
            "program_year": 2018, 
            "id": 5288972474384384
        }, 
        "text": "Here's the link to the PR\nhttps://github.com/openMF/community-app/pull/3023\n\nPlease review. :)", 
        "created": "2018-11-04T17:00:20Z", 
        "task_definition_name": "Mifos - Bug Fix: On employee creation, \"joined on\" field has no sign of showing it mandatory", 
        "organization_id": 4752143387983872, 
        "author_is_student": true, 
        "new_task_instance_status": 1, 
        "author_id": 5288972474384384, 
        "id": 6285986418917376, 
        "old_task_instance_status": 1, 
        "attachments": []
    }, 
    {
        "is_tombstoned": false, 
        "kind": 1, 
        "program_year": 2018, 
        "task_instance_id": 5056383587188736, 
        "author": {
            "display_name": "Malaal Dehlvi", 
            "program_year": 2018, 
            "id": 5288972474384384
        }, 
        "text": "", 
        "created": "2018-11-04T16:29:05Z", 
        "task_definition_name": "Mifos - Bug Fix: On employee creation, \"joined on\" field has no sign of showing it mandatory", 
        "organization_id": 4752143387983872, 
        "author_is_student": true, 
        "new_task_instance_status": 1, 
        "author_id": 5288972474384384, 
        "id": 4657938867159040, 
        "old_task_instance_status": 1, 
        "attachments": []
    }
]